djtools/__init__.py
djtools/blog/__init__.py
djtools/blog/admin.py
djtools/blog/apps.py
djtools/blog/models.py
djtools/blog/urls.py
djtools/blog/utils.py
djtools/blog/views.py
djtools/blog/migrations/0001_initial.py
djtools/blog/migrations/__init__.py
djtools/blog/templates/djtools/blog/post_detail.html
djtools/blog/templates/djtools/blog/post_list.html
django_tools_blog-1.0.1.dist-info/LICENSE
django_tools_blog-1.0.1.dist-info/METADATA
django_tools_blog-1.0.1.dist-info/WHEEL
django_tools_blog-1.0.1.dist-info/top_level.txt
django_tools_blog-1.0.1.dist-info/RECORD
